CHANGES.txt
LICENSE.txt
MANIFEST.in
README.rst
setup.cfg
setup.py
setupinfo.py
PyAMF.egg-info/PKG-INFO
PyAMF.egg-info/SOURCES.txt
PyAMF.egg-info/dependency_links.txt
PyAMF.egg-info/not-zip-safe
PyAMF.egg-info/requires.txt
PyAMF.egg-info/top_level.txt
cpyamf/__init__.py
cpyamf/amf0.c
cpyamf/amf0.pxd
cpyamf/amf0.pyx
cpyamf/amf3.c
cpyamf/amf3.pxd
cpyamf/amf3.pyx
cpyamf/codec.c
cpyamf/codec.pxd
cpyamf/codec.pyx
cpyamf/util.c
cpyamf/util.pxd
cpyamf/util.pyx
doc/Makefile
doc/about.rst
doc/bugs.rst
doc/conf.py
doc/contents.rst
doc/install.rst
doc/license.rst
doc/make.bat
doc/architecture/adapters.rst
doc/architecture/attributecontrol.rst
doc/architecture/classmapping.rst
doc/architecture/future.rst
doc/architecture/index.rst
doc/architecture/overview.rst
doc/architecture/typemap.rst
doc/architecture/examples/adapters/myadapter.py
doc/architecture/examples/adapters/mymodule.py
doc/architecture/examples/attribute-control/iexternalizable.py
doc/architecture/examples/attribute-control/models1.py
doc/architecture/examples/attribute-control/models2.py
doc/architecture/examples/attribute-control/models3.py
doc/architecture/examples/attribute-control/proxied-attr.py
doc/architecture/examples/attribute-control/server.py
doc/architecture/examples/attribute-control/static-attr.py
doc/architecture/examples/attribute-control/synonym.py
doc/architecture/examples/attribute-control/whitelist.py
doc/architecture/examples/class-mapping/alias-decorator.py
doc/architecture/examples/class-mapping/example-classes.as
doc/architecture/examples/class-mapping/example-classes.py
doc/community/download.rst
doc/community/index.rst
doc/community/irc.rst
doc/community/mailinglist.rst
doc/community/maintainers.rst
doc/community/team.rst
doc/community/thanks.rst
doc/html/defindex.html
doc/html/layout.html
doc/html/tutorials.html
doc/html/static/logo.png
doc/html/static/pyamf.ico
doc/tutorials/index.rst
doc/tutorials/actionscript/addressbook.rst
doc/tutorials/actionscript/bytearray.rst
doc/tutorials/actionscript/geoip.rst
doc/tutorials/actionscript/guestbook.rst
doc/tutorials/actionscript/index.rst
doc/tutorials/actionscript/ohloh.rst
