Metadata-Version: 1.1
Name: PyAMF
Version: 0.8.0
Summary: AMF support for Python
Home-page: http://pyamf.org
Author: The PyAMF Project
Author-email: users@pyamf.org
License: MIT License
Keywords: amf amf0 amf3 flex flash remoting rpc http flashplayer air bytearray
Platform: UNKNOWN
Classifier: Framework :: Django
Classifier: Framework :: Pylons
Classifier: Framework :: Twisted
Classifier: Intended Audience :: Developers
Classifier: Intended Audience :: Information Technology
Classifier: License :: OSI Approved :: MIT License
Classifier: Natural Language :: English
Classifier: Operating System :: OS Independent
Classifier: Programming Language :: C
Classifier: Programming Language :: Python
Classifier: Programming Language :: Cython
Classifier: Programming Language :: Python :: 2.4
Classifier: Programming Language :: Python :: 2.5
Classifier: Programming Language :: Python :: 2.6
Classifier: Programming Language :: Python :: 2.7
Classifier: Topic :: Internet :: WWW/HTTP :: WSGI :: Application
Classifier: Topic :: Software Development :: Libraries :: Python Modules
Classifier: Development Status :: 5 - Production/Stable
